CTkSeparator/__init__.py
CTkSeparator/ctk_separator.py
ctkseparator-1.5.1.dist-info/licenses/LICENSE
ctkseparator-1.5.1.dist-info/METADATA
ctkseparator-1.5.1.dist-info/WHEEL
ctkseparator-1.5.1.dist-info/top_level.txt
ctkseparator-1.5.1.dist-info/RECORD
