Metadata-Version: 2.4
Name: CTkSeparator
Version: 1.5.1
Summary: A customizable separator widget for CustomTkinter
Home-page: https://github.com/AJ-cubes/CTkSeparator/
Author: AJ-cubes
Author-email: ajcubes33@gmail.com
License: MIT
Keywords: separator,customtkinter,GUI,widget
Classifier: Programming Language :: Python :: 3
Classifier: License :: OSI Approved :: MIT License
Classifier: Operating System :: OS Independent
Requires-Python: >=3.6
License-File: LICENSE
Requires-Dist: customtkinter
Requires-Dist: pillow
Dynamic: author
Dynamic: author-email
Dynamic: classifier
Dynamic: description
Dynamic: description-content-type
Dynamic: home-page
Dynamic: keywords
Dynamic: license
Dynamic: license-file
Dynamic: requires-dist
Dynamic: requires-python
Dynamic: summary
